README.rst
setup.py
challonge2elo/__init__.py
challonge2elo.egg-info/PKG-INFO
challonge2elo.egg-info/SOURCES.txt
challonge2elo.egg-info/dependency_links.txt
challonge2elo.egg-info/entry_points.txt
challonge2elo.egg-info/requires.txt
challonge2elo.egg-info/top_level.txt