Metadata-Version: 1.0
Name: challonge2elo
Version: 0.1.0
Summary: Elo ratings from Challonge tournament results.
Home-page: https://github.com/mtgray/challonge2elo
Author: Matthew Gray
Author-email: UNKNOWN
License: MIT
Platform: UNKNOWN
